workwithimage.py
workwithimage-0.0.4.1.dist-info/METADATA
workwithimage-0.0.4.1.dist-info/WHEEL
workwithimage-0.0.4.1.dist-info/RECORD
