Metadata-Version: 2.1
Name: workwithimage
Version: 0.0.4.1
Summary: Library for working with images based on Pillow
Author: Nova D Andrew
Author-email: andrew.d.nova@icloud.com
Requires-Python: >=3.6,<4.0
Classifier: Programming Language :: Python :: 3
Classifier: Programming Language :: Python :: 3.6
Classifier: Programming Language :: Python :: 3.7
Classifier: Programming Language :: Python :: 3.8
Classifier: Programming Language :: Python :: 3.9
Classifier: Programming Language :: Python :: 3.10
Classifier: Programming Language :: Python :: 3.11
Classifier: Programming Language :: Python :: 3.12
